pteredactyl/__init__.py
pteredactyl/defaults.py
pteredactyl/exceptions.py
pteredactyl/mappings.py
pteredactyl/py.typed
pteredactyl/redactor.py
pteredactyl/regex_check_functions.py
pteredactyl/regex_entities.py
pteredactyl/support.py
pteredactyl/recognisers/pteredactyl_recogniser.py
pteredactyl/recognisers/support.py
pteredactyl/recognisers/transformers_recogniser.py
pteredactyl/replacement_lists/generate_lists.py
pteredactyl/replacement_lists/raw/uk-towns-and-cities-a.txt
pteredactyl-1.1.0.dist-info/METADATA
pteredactyl-1.1.0.dist-info/WHEEL
pteredactyl-1.1.0.dist-info/RECORD
