Metadata-Version: 2.4
Name: pteredactyl
Version: 1.1.0
Summary: Pteredactyl is a tool for NER based redaction of personally identifiable information in text
Author-email: Cai Davis <cai.davis@uhs.nhs.uk>, Michael George <michael.george@uhs.nhs.uk>
License-Expression: MIT
Requires-Python: <3.14,>=3.11
Requires-Dist: iprogress<0.5,>=0.4
Requires-Dist: ipykernel<7,>=6.26.0
Requires-Dist: ipywidgets<9,>=8.1.1
Requires-Dist: pandas<3,>=2.2.0
Requires-Dist: pip>=25.3
Requires-Dist: presidio-analyzer<3,>=2.2.33
Requires-Dist: presidio-anonymizer<3,>=2.2.33
Requires-Dist: spacy-legacy<4,>=3.0.12
Requires-Dist: spacy-loggers<2,>=1.0.5
Requires-Dist: spacy<4,>=3.8.2
Requires-Dist: torch
Requires-Dist: torchaudio
Requires-Dist: torchvision
Requires-Dist: tqdm<5,>=4.66.1
Requires-Dist: transformers<5,>=4.34.1
